timesplitter/__init__.py
timesplitter/timesplitter.py
timesplitter-1.0.4.dist-info/LICENSE.txt
timesplitter-1.0.4.dist-info/WHEEL
timesplitter-1.0.4.dist-info/METADATA
timesplitter-1.0.4.dist-info/RECORD
